bqs/__init__.py
bqs/algorithms/__init__.py
bqs/algorithms/qaoa.py
bqs/generators/__init__.py
bqs/generators/cartesian.py
bqs/generators/khot.py
bqs/generators/qubos.py
bqs/quantum_tools/__init__.py
bqs/quantum_tools/abstract_quantum_objects.py
bqs/quantum_tools/cirq_quantum_objects.py
bqs/quantum_tools/qiskit_quantum_objects.py
bqs/utils/__init__.py
bqs/utils/optimizers.py
bqs/utils/qaoa_utils.py
bqs/utils/solver_utils.py
bqs/utils/vqa_utils.py
bqs-0.1.10.dist-info/LICENSE
bqs-0.1.10.dist-info/METADATA
bqs-0.1.10.dist-info/WHEEL
bqs-0.1.10.dist-info/top_level.txt
bqs-0.1.10.dist-info/RECORD
