Metadata-Version: 2.2
Name: bqs
Version: 0.1.10
Summary: Better Quantum Software
Home-page: https://github.com/MichiCatte/bqs.git
Author: Michele Cattelan
Author-email: michelecat97@gmail.com
License: License :: OSI Approved :: MIT License
Classifier: Development Status :: 2 - Pre-Alpha
Classifier: Intended Audience :: Developers
Classifier: Intended Audience :: Science/Research
Classifier: Programming Language :: Python :: 3.9
Classifier: Programming Language :: Python :: 3.10
License-File: LICENSE
Requires-Dist: dimod>=0.12.18
Requires-Dist: cirq>=1.4.1
Requires-Dist: bidict==0.23.1
Dynamic: author
Dynamic: author-email
Dynamic: classifier
Dynamic: description
Dynamic: description-content-type
Dynamic: home-page
Dynamic: license
Dynamic: requires-dist
Dynamic: summary
